{
  "minecraft:recipes/decorations/polished_deepslate_wall_from_cobbled_deepslate_stonecutting": {
    "criteria": {
      "has_cobbled_deepslate": "2021-08-26 21:44:08 +0900"
    },
    "done": true
  },
  "minecraft:recipes/building_blocks/deepslate_tile_slab_from_polished_deepslate_stonecutting": {
    "criteria": {
      "has_polished_deepslate": "2021-08-26 21:19:46 +0900"
    },
    "done": true
  },
  "minecraft:recipes/decorations/deepslate_tile_wall_from_polished_deepslate_stonecutting": {
    "criteria": {
      "has_polished_deepslate": "2021-08-26 21:19:46 +0900"
    },
    "done": true
  },
  "minecraft:recipes/redstone/repeater": {
    "criteria": {
      "has_redstone_torch": "2021-08-26 21:28:04 +0900"
    },
    "done": true
  },
  "minecraft:recipes/building_blocks/smooth_stone_slab": {
    "criteria": {
      "has_smooth_stone": "2021-08-26 21:47:30 +0900"
    },
    "done": true
  },
  "minecraft:recipes/building_blocks/polished_deepslate": {
    "criteria": {
      "has_cobbled_deepslate": "2021-08-26 21:44:08 +0900"
    },
    "done": true
  },
  "minecraft:recipes/decorations/polished_deepslate_wall_from_polished_deepslate_stonecutting": {
    "criteria": {
      "has_polished_deepslate": "2021-08-26 21:19:46 +0900"
    },
    "done": true
  },
  "minecraft:recipes/building_blocks/chiseled_deepslate_from_cobbled_deepslate_stonecutting": {
    "criteria": {
      "has_cobbled_deepslate": "2021-08-26 21:44:08 +0900"
    },
    "done": true
  },
  "minecraft:recipes/decorations/deepslate_tile_wall_from_cobbled_deepslate_stonecutting": {
    "criteria": {
      "has_cobbled_deepslate": "2021-08-26 21:44:08 +0900"
    },
    "done": true
  },
  "minecraft:recipes/building_blocks/deepslate_brick_stairs_from_polished_deepslate_stonecutting": {
    "criteria": {
      "has_polished_deepslate": "2021-08-26 21:19:46 +0900"
    },
    "done": true
  },
  "minecraft:story/mine_stone": {
    "criteria": {
      "get_stone": "2021-08-26 21:44:08 +0900"
    },
    "done": true
  },
  "minecraft:recipes/decorations/furnace": {
    "criteria": {
      "has_cobblestone": "2021-08-26 21:44:08 +0900"
    },
    "done": true
  },
  "minecraft:recipes/decorations/deepslate_brick_wall_from_cobbled_deepslate_stonecutting": {
    "criteria": {
      "has_cobbled_deepslate": "2021-08-26 21:44:08 +0900"
    },
    "done": true
  },
  "minecraft:recipes/building_blocks/deepslate_bricks_from_cobbled_deepslate_stonecutting": {
    "criteria": {
      "has_cobbled_deepslate": "2021-08-26 21:44:08 +0900"
    },
    "done": true
  },
  "minecraft:recipes/brewing/cauldron": {
    "criteria": {
      "has_water_bucket": "2021-08-26 21:45:36 +0900"
    },
    "done": true
  },
  "minecraft:recipes/building_blocks/deepslate_brick_stairs_from_cobbled_deepslate_stonecutting": {
    "criteria": {
      "has_cobbled_deepslate": "2021-08-26 21:44:08 +0900"
    },
    "done": true
  },
  "minecraft:adventure/adventuring_time": {
    "criteria": {
      "minecraft:river": "2021-08-26 20:12:04 +0900",
      "minecraft:plains": "2021-08-26 19:54:02 +0900"
    },
    "done": false
  },
  "minecraft:recipes/decorations/armor_stand": {
    "criteria": {
      "has_stone_slab": "2021-08-26 21:46:58 +0900"
    },
    "done": true
  },
  "minecraft:recipes/decorations/light_blue_stained_glass_pane": {
    "criteria": {
      "has_glass": "2021-08-26 21:29:18 +0900"
    },
    "done": true
  },
  "minecraft:recipes/decorations/deepslate_brick_wall_from_polished_deepslate_stonecutting": {
    "criteria": {
      "has_polished_deepslate": "2021-08-26 21:19:46 +0900"
    },
    "done": true
  },
  "minecraft:recipes/decorations/blast_furnace": {
    "criteria": {
      "has_smooth_stone": "2021-08-26 21:47:30 +0900"
    },
    "done": true
  },
  "minecraft:recipes/building_blocks/cobbled_deepslate_stairs": {
    "criteria": {
      "has_cobbled_deepslate": "2021-08-26 21:44:08 +0900"
    },
    "done": true
  },
  "minecraft:recipes/building_blocks/deepslate_tile_stairs_from_polished_deepslate_stonecutting": {
    "criteria": {
      "has_polished_deepslate": "2021-08-26 21:19:46 +0900"
    },
    "done": true
  },
  "minecraft:recipes/transportation/birch_boat": {
    "criteria": {
      "in_water": "2021-08-26 20:00:00 +0900"
    },
    "done": true
  },
  "minecraft:recipes/combat/stone_sword": {
    "criteria": {
      "has_cobblestone": "2021-08-26 21:44:08 +0900"
    },
    "done": true
  },
  "minecraft:recipes/building_blocks/cobbled_deepslate_slab": {
    "criteria": {
      "has_cobbled_deepslate": "2021-08-26 21:44:08 +0900"
    },
    "done": true
  },
  "minecraft:recipes/building_blocks/polished_deepslate_slab": {
    "criteria": {
      "has_polished_deepslate": "2021-08-26 21:19:46 +0900"
    },
    "done": true
  },
  "minecraft:recipes/building_blocks/deepslate_tile_slab_from_cobbled_deepslate_stonecutting": {
    "criteria": {
      "has_cobbled_deepslate": "2021-08-26 21:44:08 +0900"
    },
    "done": true
  },
  "minecraft:recipes/building_blocks/cobbled_deepslate_stairs_from_cobbled_deepslate_stonecutting": {
    "criteria": {
      "has_cobbled_deepslate": "2021-08-26 21:44:08 +0900"
    },
    "done": true
  },
  "minecraft:recipes/transportation/acacia_boat": {
    "criteria": {
      "in_water": "2021-08-26 20:00:00 +0900"
    },
    "done": true
  },
  "minecraft:recipes/tools/stone_pickaxe": {
    "criteria": {
      "has_cobblestone": "2021-08-26 21:44:08 +0900"
    },
    "done": true
  },
  "minecraft:recipes/building_blocks/deepslate_brick_slab_from_cobbled_deepslate_stonecutting": {
    "criteria": {
      "has_cobbled_deepslate": "2021-08-26 21:44:08 +0900"
    },
    "done": true
  },
  "minecraft:recipes/transportation/jungle_boat": {
    "criteria": {
      "in_water": "2021-08-26 20:00:00 +0900"
    },
    "done": true
  },
  "minecraft:recipes/transportation/spruce_boat": {
    "criteria": {
      "in_water": "2021-08-26 20:00:00 +0900"
    },
    "done": true
  },
  "minecraft:recipes/tools/stone_shovel": {
    "criteria": {
      "has_cobblestone": "2021-08-26 21:44:08 +0900"
    },
    "done": true
  },
  "minecraft:recipes/decorations/polished_deepslate_wall": {
    "criteria": {
      "has_polished_deepslate": "2021-08-26 21:19:46 +0900"
    },
    "done": true
  },
  "minecraft:recipes/tools/stone_hoe": {
    "criteria": {
      "has_cobblestone": "2021-08-26 21:44:08 +0900"
    },
    "done": true
  },
  "minecraft:recipes/transportation/dark_oak_boat": {
    "criteria": {
      "in_water": "2021-08-26 20:00:00 +0900"
    },
    "done": true
  },
  "minecraft:recipes/building_blocks/polished_deepslate_stairs_from_polished_deepslate_stonecutting": {
    "criteria": {
      "has_polished_deepslate": "2021-08-26 21:19:46 +0900"
    },
    "done": true
  },
  "minecraft:recipes/building_blocks/polished_deepslate_from_cobbled_deepslate_stonecutting": {
    "criteria": {
      "has_cobbled_deepslate": "2021-08-26 21:44:08 +0900"
    },
    "done": true
  },
  "minecraft:recipes/building_blocks/deepslate": {
    "criteria": {
      "has_cobbled_deepslate": "2021-08-26 21:44:08 +0900"
    },
    "done": true
  },
  "minecraft:recipes/building_blocks/deepslate_bricks_from_polished_deepslate_stonecutting": {
    "criteria": {
      "has_polished_deepslate": "2021-08-26 21:19:46 +0900"
    },
    "done": true
  },
  "minecraft:recipes/building_blocks/deepslate_bricks": {
    "criteria": {
      "has_polished_deepslate": "2021-08-26 21:19:46 +0900"
    },
    "done": true
  },
  "minecraft:recipes/building_blocks/polished_deepslate_slab_from_cobbled_deepslate_stonecutting": {
    "criteria": {
      "has_cobbled_deepslate": "2021-08-26 21:44:08 +0900"
    },
    "done": true
  },
  "minecraft:recipes/building_blocks/polished_deepslate_stairs_from_cobbled_deepslate_stonecutting": {
    "criteria": {
      "has_cobbled_deepslate": "2021-08-26 21:44:08 +0900"
    },
    "done": true
  },
  "minecraft:recipes/building_blocks/deepslate_tiles_from_polished_deepslate_stonecutting": {
    "criteria": {
      "has_polished_deepslate": "2021-08-26 21:19:46 +0900"
    },
    "done": true
  },
  "minecraft:recipes/decorations/cobbled_deepslate_wall_from_cobbled_deepslate_stonecutting": {
    "criteria": {
      "has_cobbled_deepslate": "2021-08-26 21:44:08 +0900"
    },
    "done": true
  },
  "minecraft:recipes/building_blocks/polished_deepslate_stairs": {
    "criteria": {
      "has_polished_deepslate": "2021-08-26 21:19:46 +0900"
    },
    "done": true
  },
  "minecraft:recipes/building_blocks/polished_deepslate_slab_from_polished_deepslate_stonecutting": {
    "criteria": {
      "has_polished_deepslate": "2021-08-26 21:19:46 +0900"
    },
    "done": true
  },
  "minecraft:recipes/building_blocks/deepslate_brick_slab_from_polished_deepslate_stonecutting": {
    "criteria": {
      "has_polished_deepslate": "2021-08-26 21:19:46 +0900"
    },
    "done": true
  },
  "minecraft:recipes/building_blocks/cobbled_deepslate_slab_from_cobbled_deepslate_stonecutting": {
    "criteria": {
      "has_cobbled_deepslate": "2021-08-26 21:44:08 +0900"
    },
    "done": true
  },
  "minecraft:recipes/transportation/oak_boat": {
    "criteria": {
      "in_water": "2021-08-26 20:00:00 +0900"
    },
    "done": true
  },
  "minecraft:recipes/building_blocks/deepslate_tile_stairs_from_cobbled_deepslate_stonecutting": {
    "criteria": {
      "has_cobbled_deepslate": "2021-08-26 21:44:08 +0900"
    },
    "done": true
  },
  "minecraft:recipes/decorations/cobbled_deepslate_wall": {
    "criteria": {
      "has_cobbled_deepslate": "2021-08-26 21:44:08 +0900"
    },
    "done": true
  },
  "minecraft:recipes/building_blocks/deepslate_tiles_from_cobbled_deepslate_stonecutting": {
    "criteria": {
      "has_cobbled_deepslate": "2021-08-26 21:44:08 +0900"
    },
    "done": true
  },
  "minecraft:recipes/tools/stone_axe": {
    "criteria": {
      "has_cobblestone": "2021-08-26 21:44:08 +0900"
    },
    "done": true
  },
  "minecraft:recipes/misc/gold_ingot_from_gold_block": {
    "criteria": {
      "has_gold_block": "2021-08-26 21:43:42 +0900"
    },
    "done": true
  },
  "useful_tools:entered_world": {
    "criteria": {
      "enter": "2021-08-26 19:54:02 +0900"
    },
    "done": true
  },
  "minecraft:recipes/building_blocks/smooth_stone_slab_from_smooth_stone_stonecutting": {
    "criteria": {
      "has_smooth_stone": "2021-08-26 21:47:30 +0900"
    },
    "done": true
  },
  "DataVersion": 2730
}